vivaldy/__init__.py
vivaldy/main.py
vivaldy/vivaldy.py
vivaldy-0.1.1a0.dist-info/licenses/LICENSE.md
vivaldy-0.1.1a0.dist-info/METADATA
vivaldy-0.1.1a0.dist-info/WHEEL
vivaldy-0.1.1a0.dist-info/top_level.txt
vivaldy-0.1.1a0.dist-info/RECORD
