Metadata-Version: 2.4
Name: vivaldy
Version: 0.1.1a0
Summary: Add music on hold to your Python code
Author-email: Yann <phd@yannziegler.com>
License-Expression: EUPL-1.2
Project-URL: Homepage, https://github.com/yannziegler/vivaldy
Project-URL: Issues, https://github.com/yannziegler/vivaldy/issues
Keywords: music on hold,Vivaldi,musique d'attente
Classifier: Development Status :: 3 - Alpha
Classifier: Programming Language :: Python :: 3
Classifier: Operating System :: OS Independent
Requires-Python: >=3.9
License-File: LICENSE.md
Requires-Dist: audioop-lts>=0.2.2
Requires-Dist: ffmpeg-python>=0.2.0
Requires-Dist: playsound3>=3.3.0
Requires-Dist: pydub>=0.25.1
Requires-Dist: pytubefix>=10.3.6
Dynamic: license-file
